shyft/dashboard/__init__.py
shyft/dashboard/__main__.py
shyft/dashboard/apps/__init__.py
shyft/dashboard/apps/start_bokeh_apps.py
shyft/dashboard/apps/dtss_viewer/__init__.py
shyft/dashboard/apps/dtss_viewer/dtsc_helper_functions.py
shyft/dashboard/apps/dtss_viewer/dtss_viewer_app.py
shyft/dashboard/apps/dtss_viewer/widgets.py
shyft/dashboard/apps/water_route_app/__init__.py
shyft/dashboard/apps/water_route_app/example_hps.py
shyft/dashboard/apps/water_route_app/simplified_water_route.py
shyft/dashboard/apps/water_route_app/water_route_app.py
shyft/dashboard/base/__init__.py
shyft/dashboard/base/app.py
shyft/dashboard/base/constants.py
shyft/dashboard/base/gate_model.py
shyft/dashboard/base/gate_presenter.py
shyft/dashboard/base/hashable.py
shyft/dashboard/base/ports.py
shyft/dashboard/base/selector_model.py
shyft/dashboard/base/selector_presenter.py
shyft/dashboard/base/selector_views.py
shyft/dashboard/entry_points/__init__.py
shyft/dashboard/entry_points/entry_points.py
shyft/dashboard/entry_points/start_bokeh_examples.py
shyft/dashboard/entry_points/visualize_apps.py
shyft/dashboard/examples/__init__.py
shyft/dashboard/examples/app.py
shyft/dashboard/examples/basic_bokeh_app.py
shyft/dashboard/examples/date_selector.py
shyft/dashboard/examples/figure_legend.py
shyft/dashboard/examples/gates.py
shyft/dashboard/examples/hover_tool.py
shyft/dashboard/examples/label_selector.py
shyft/dashboard/examples/message_viewer.py
shyft/dashboard/examples/multi_select_tabs.py
shyft/dashboard/examples/ports.py
shyft/dashboard/examples/selector_model.py
shyft/dashboard/examples/selector_views.py
shyft/dashboard/examples/slider_selector.py
shyft/dashboard/examples/test_data_generator.py
shyft/dashboard/examples/time_interval_selector_slider.py
shyft/dashboard/examples/time_series_period_selector.py
shyft/dashboard/examples/time_series_scatter_renderer.py
shyft/dashboard/examples/time_series_viewer.py
shyft/dashboard/examples/ts_viewer_background_data_renderer.py
shyft.time_series-13.0.3.dist-info/METADATA
shyft.time_series-13.0.3.dist-info/WHEEL
shyft.time_series-13.0.3.dist-info/top_level.txt
shyft.time_series-13.0.3.dist-info/RECORD
