Metadata-Version: 2.1
Name: shyft.time-series
Version: 13.0.3
Summary: Open Shyft for advanced high performance time-series handling
Home-page: https://gitlab.com/shyft-os/shyft
Author: shyft
Author-email: sigbjorn.helset@gmail.com
License: LGPL v3
Platform: linux-x86_64
Requires: numpy
Requires-Dist: numpy
